jimmyskitchen/__init__.py
jimmyskitchen/check_chart_extended.py
jimmyskitchen/check_returns_extented.py
jimmyskitchen/check_top_gainers_losers.py
jimmyskitchen/check_volume_change.py
jimmyskitchen/git_utils.py
jimmyskitchen/import_data.py
jimmyskitchen/main.py
jimmyskitchen/resources.py
jimmyskitchen/scrap_tickers.py
jimmyskitchen-0.0.1.dist-info/LICENSE
jimmyskitchen-0.0.1.dist-info/METADATA
jimmyskitchen-0.0.1.dist-info/WHEEL
jimmyskitchen-0.0.1.dist-info/top_level.txt
jimmyskitchen-0.0.1.dist-info/RECORD
