Metadata-Version: 2.1
Name: jimmyskitchen
Version: 0.0.1
Summary: Framework for trading US stocks
Home-page: https://github.com/JuliusLhamo/JimsKitchenPublic
Author: Julius Landes
Author-email: Lhamo.Landes@campus.lmu.de
Classifier: Programming Language :: Python :: 3
Classifier: License :: OSI Approved :: MIT License
Classifier: Operating System :: OS Independent
License-File: LICENSE
Requires-Dist: GitPython
Requires-Dist: pandas
Requires-Dist: plotly
Requires-Dist: numpy
